ovos_translate_server_plugin/__init__.py
ovos_translate_server_plugin/version.py
ovos_translate_server_plugin-0.0.5.dist-info/licenses/LICENSE
ovos_translate_server_plugin-0.0.5.dist-info/METADATA
ovos_translate_server_plugin-0.0.5.dist-info/WHEEL
ovos_translate_server_plugin-0.0.5.dist-info/entry_points.txt
ovos_translate_server_plugin-0.0.5.dist-info/top_level.txt
ovos_translate_server_plugin-0.0.5.dist-info/RECORD
